Metadata-Version: 2.4
Name: vaillant-netatmo-api-reloaded
Version: 0.12.5
Summary: Python 3 library for managing Vaillant thermostats using the Netatmo API.
Author: Olivier Toussaint
Project-URL: Homepage, https://github.com/MislavMandaric/vaillant-netatmo-api
Project-URL: Issues, https://github.com/MislavMandaric/vaillant-netatmo-api/issues
Classifier: Programming Language :: Python :: 3
Classifier: License :: OSI Approved :: MIT License
Classifier: Operating System :: OS Independent
Requires-Python: >=3.12
License-File: LICENSE
Requires-Dist: httpx>=0.18.2
Requires-Dist: tenacity>=8.0.1
Dynamic: license-file
